password/__init__.py
GodPasswordGeneretorPrivatAmirz-1.dist-info/LICENCE.txt
GodPasswordGeneretorPrivatAmirz-1.dist-info/METADATA
GodPasswordGeneretorPrivatAmirz-1.dist-info/WHEEL
GodPasswordGeneretorPrivatAmirz-1.dist-info/top_level.txt
GodPasswordGeneretorPrivatAmirz-1.dist-info/RECORD
