Metadata-Version: 2.1
Name: GodPasswordGeneretorPrivatAmirz
Version: 1
Summary: generede password
Author: hunter
Author-email: amirreurple649@gmail.com
Classifier: Programming Language :: Python :: 3
Classifier: License :: OSI Approved :: MIT License
Classifier: Operating System :: OS Independent
License-File: LICENCE.txt
